tensor_img_utils/__init__.py
TensorImgUtils-0.1.2.dist-info/LICENSE
TensorImgUtils-0.1.2.dist-info/METADATA
TensorImgUtils-0.1.2.dist-info/WHEEL
TensorImgUtils-0.1.2.dist-info/top_level.txt
TensorImgUtils-0.1.2.dist-info/RECORD
